mldl/__init__.py
mldl/__main__.py
mldl/cli/__init__.py
mldl/cli/cli_main.py
mldl/cli/tests/__init__.py
mldl/cli/tests/cli_main_test.py
mldl/datarepo/__init__.py
mldl/datarepo/mappers/__init__.py
mldl/datarepo/mappers/csv_to_file.py
mldl/datarepo/mappers/file_to_file.py
mldl/datarepo/mappers/static_file_mapper.py
mldl/datarepo/storage/__init__.py
mldl/datarepo/storage/azure_blob.py
mldl/datarepo/storage/storage.py
mldl/datarepo/storage/storage_utils.py
mldl/datarepo/tests/__init__.py
mldl/datarepo/tests/azure_blob_storage_test.py
mldl/datarepo/tests/mappers_test.py
mldl/datarepo/tests/storage_utils_test.py
mldl/requirements.txt
mldl-0.0.6.dist-info/entry_points.txt
mldl-0.0.6.dist-info/LICENSE
mldl-0.0.6.dist-info/WHEEL
mldl-0.0.6.dist-info/METADATA
mldl-0.0.6.dist-info/RECORD
