Metadata-Version: 2.1
Name: mldl
Version: 0.0.6
Summary: Machine Learning Data Lineage tool (MLDL)
License: MIT
Author: Vlad Kolesnikov
Requires-Python: >=3.6,<4.0
Classifier: License :: OSI Approved :: MIT License
Classifier: Programming Language :: Python :: 3
Classifier: Programming Language :: Python :: 3.6
Classifier: Programming Language :: Python :: 3.7
Classifier: Programming Language :: Python :: 3.8
Classifier: Programming Language :: Python :: 3.9
Requires-Dist: PyYAML (>=5.3,<6.0)
Requires-Dist: azure-storage-blob (>=12.5,<13.0)
